imgann/__init__.py
imgann/convert.py
imgann/sample.py
imgann/operators/__init__.py
imgann/operators/coco.py
imgann/operators/csv.py
imgann/operators/imgdata.py
imgann/operators/operator.py
imgann/operators/pascalvoc.py
imgann/operators/yolo.py
ImgAnn-0.8.1.dist-info/LICENSE
ImgAnn-0.8.1.dist-info/METADATA
ImgAnn-0.8.1.dist-info/WHEEL
ImgAnn-0.8.1.dist-info/top_level.txt
ImgAnn-0.8.1.dist-info/RECORD
