Metadata-Version: 2.1
Name: ImgAnn
Version: 0.8.1
Summary: Image annotation file operation provider. [Documentation](https://imgann.readthedocs.io/en/latest/index.html)
Home-page: https://github.com/nipdep/imgann.git
Author: nipdep
Author-email: nipdep <nipun1deelaka@gmail.com>
Project-URL: Bug Reports, https://github.com/nipdep/imgann/issues
Project-URL: Source, https://github.com/nipdep/imgann/
Keywords: s,a,m,p,l,e,,, ,s,e,t,u,p,t,o,o,l,s,,, ,d,e,v,e,l,o,p,m,e,n,t
Requires-Python: >=3.6, <4
License-File: LICENSE
Requires-Dist: numpy
Requires-Dist: pandas
Requires-Dist: matplotlib
Requires-Dist: opencv-python
Requires-Dist: pillow
Provides-Extra: dev
Requires-Dist: check-manifest ; extra == 'dev'
Requires-Dist: pytest (>=3.7) ; extra == 'dev'
Provides-Extra: test
Requires-Dist: coverage ; extra == 'test'
Requires-Dist: unittest ; extra == 'test'
